common/__init__.py
common/common/__init__.py
common/common/array_head.py
common/common/array_info.py
common/common/base_data.py
common/common/box.py
common/common/copy_grid.py
common/common/data_format.py
common/common/dimension.py
common/common/text_format.py
common/common/unit_converter.py
common/model/__init__.py
common/model/base_enum.py
common/model/common/__init__.py
common/model/common/message_type.py
common/model/common/unit_system.py
common/model/reservoir/__init__.py
common/model/reservoir/dimension_type.py
common/model/reservoir/justify_type.py
common/model/reservoir/module_type.py
common/model/reservoir/perforation_type.py
common/model/reservoir/perm_type.py
common/model/reservoir/process_type.py
common/model/reservoir/product_column_name.py
common/model/reservoir/product_unit.py
common/model/reservoir/rel_permeate_type.py
common/model/reservoir/unit_convert_factor.py
common/model/reservoir/unit_type.py
common/model/reservoir/user_time_type.py
common/model/reservoir/well_control_type.py
common/model/reservoir/well_group_model.py
common/model/reservoir/well_tatio_limit_type.py
common/reservoir/__init__.py
common/reservoir/comp_module/__init__.py
common/reservoir/comp_module/comp_module.py
common/reservoir/comp_module/module_control.py
common/reservoir/grid/__init__.py
common/reservoir/grid/dimension_value.py
common/reservoir/grid/fipnum.py
common/reservoir/grid/grid.py
common/reservoir/grid/perm.py
common/reservoir/grid/poro.py
common/reservoir/grid/tops.py
common/reservoir/props/__init__.py
common/reservoir/props/density.py
common/reservoir/props/props.py
common/reservoir/props/pvdg.py
common/reservoir/props/pvto.py
common/reservoir/props/pvtw.py
common/reservoir/props/rel_permeate_model.py
common/reservoir/props/rock.py
common/reservoir/props/sgof.py
common/reservoir/props/swof.py
common/reservoir/result/__init__.py
common/reservoir/result/wel_status.py
common/reservoir/result/well_product_record.py
common/reservoir/result/well_production.py
mag_common-0.1.2.dist-info/METADATA
mag_common-0.1.2.dist-info/WHEEL
mag_common-0.1.2.dist-info/top_level.txt
mag_common-0.1.2.dist-info/RECORD
