Metadata-Version: 2.1
Name: mag_common
Version: 0.1.2
Summary: 通用信息
Home-page: http://gitlab.magnetitech.com:8088/sources/frame/py-frame/mag_common.git
Author: xlcao
Author-email: xl_cao@hotmail.com
Classifier: Programming Language :: Python :: 3
Classifier: License :: OSI Approved :: MIT License
Classifier: Operating System :: OS Independent
Requires-Python: >=3.6
